AnquanKe2020q4Fix1/README.md
AnquanKe2020q4Fix1/__init__.py
AnquanKe2020q4Fix1/__main__.py
AnquanKe2020q4Fix1/file.epub
AnquanKe2020q4Fix1/index.html
AnquanKe2020q4Fix1/css/__init__.py
AnquanKe2020q4Fix1/css/annotations.css
AnquanKe2020q4Fix1/css/main.css
AnquanKe2020q4Fix1/css/normalize.css
AnquanKe2020q4Fix1/css/popup.css
AnquanKe2020q4Fix1/font/__init__.py
AnquanKe2020q4Fix1/font/fontello.eot
AnquanKe2020q4Fix1/font/fontello.svg
AnquanKe2020q4Fix1/font/fontello.ttf
AnquanKe2020q4Fix1/font/fontello.woff
AnquanKe2020q4Fix1/img/__init__.py
AnquanKe2020q4Fix1/img/annotator-glyph-sprite.png
AnquanKe2020q4Fix1/img/annotator-icon-sprite.png
AnquanKe2020q4Fix1/img/apple-touch-icon.png
AnquanKe2020q4Fix1/img/cancelfullscreen.png
AnquanKe2020q4Fix1/img/close.png
AnquanKe2020q4Fix1/img/fullscreen.png
AnquanKe2020q4Fix1/img/loader.gif
AnquanKe2020q4Fix1/img/menu-icon.png
AnquanKe2020q4Fix1/img/save.png
AnquanKe2020q4Fix1/img/saved.png
AnquanKe2020q4Fix1/img/settings-s.png
AnquanKe2020q4Fix1/img/settings.png
AnquanKe2020q4Fix1/img/star.png
AnquanKe2020q4Fix1/js/__init__.py
AnquanKe2020q4Fix1/js/epub.js
AnquanKe2020q4Fix1/js/epub.min.js
AnquanKe2020q4Fix1/js/epub.min.map
AnquanKe2020q4Fix1/js/hooks.min.js
AnquanKe2020q4Fix1/js/hooks.min.map
AnquanKe2020q4Fix1/js/reader.js
AnquanKe2020q4Fix1/js/reader.js.map
AnquanKe2020q4Fix1/js/reader.min.js
AnquanKe2020q4Fix1/js/reader.min.map
AnquanKe2020q4Fix1/js/hooks/__init__.py
AnquanKe2020q4Fix1/js/hooks/extensions/__init__.py
AnquanKe2020q4Fix1/js/hooks/extensions/highlight.js
AnquanKe2020q4Fix1/js/libs/__init__.py
AnquanKe2020q4Fix1/js/libs/jquery.min.js
AnquanKe2020q4Fix1/js/libs/localforage.min.js
AnquanKe2020q4Fix1/js/libs/screenfull.js
AnquanKe2020q4Fix1/js/libs/screenfull.min.js
AnquanKe2020q4Fix1/js/libs/zip.min.js
AnquanKe2020q4Fix1/js/plugins/__init__.py
AnquanKe2020q4Fix1/js/plugins/hypothesis.js
AnquanKe2020q4Fix1/js/plugins/search.js
anquan_ke_2020q4_fix1-2025.3.25.0.dist-info/METADATA
anquan_ke_2020q4_fix1-2025.3.25.0.dist-info/WHEEL
anquan_ke_2020q4_fix1-2025.3.25.0.dist-info/entry_points.txt
anquan_ke_2020q4_fix1-2025.3.25.0.dist-info/top_level.txt
anquan_ke_2020q4_fix1-2025.3.25.0.dist-info/RECORD
